{
    "blocks": [
        {
            "type": "heading",
            "level": 1,
            "text": "Lecci贸n 8.2: Limpieza profunda (Evaporadores y Condensadores)"
        },
        {
            "type": "heading",
            "level": 2,
            "text": "Introducci贸n: la importancia de la limpieza qu铆mica avanzada"
        },
        {
            "type": "paragraph",
            "text": "Los serpentines de los sistemas HVAC, ya sean de unidades interiores, exteriores, chillers o torres de enfriamiento, son componentes cr铆ticos para la transferencia t茅rmica. Con el tiempo, la acumulaci贸n de polvo, grasas, minerales, contaminantes biol贸gicos y residuos de agua reduce significativamente la eficiencia del equipo, provoca aumento del consumo el茅ctrico, sobrecarga de compresores, p茅rdida de caudal de aire y genera ruido adicional."
        },
        {
            "type": "paragraph",
            "text": "En mantenimiento profesional de nivel m谩ster, la limpieza qu铆mica no es un simple lavado superficial. Se requiere diagn贸stico del tipo de suciedad, selecci贸n precisa del agente qu铆mico, preparaci贸n de la superficie, aplicaci贸n controlada, neutralizaci贸n y enjuague para restaurar la eficiencia del serpent铆n sin da帽ar aletas, soldaduras, revestimientos o tuber铆as internas."
        },
        {
            "type": "heading",
            "level": 2,
            "text": "Tipos de contaminantes y diagn贸stico previo"
        },
        {
            "type": "paragraph",
            "text": "Antes de iniciar la limpieza, el t茅cnico profesional realiza un diagn贸stico detallado:"
        },
        {
            "type": "list",
            "style": "unordered",
            "items": [
                "Polvo y part铆culas finas: principalmente en serpentines interiores y conductos.",
                "Dep贸sitos minerales o sarro: comunes en serpentines de torres de enfriamiento y condensadores de agua.",
                "Grasas y contaminantes org谩nicos: presentes en unidades interiores de cocinas o entornos industriales.",
                "Crecimiento biol贸gico: mohos, algas o bacterias que afectan higiene y eficiencia t茅rmica."
            ]
        },
        {
            "type": "paragraph",
            "text": "El diagn贸stico se realiza mediante inspecci贸n visual, medici贸n de ca铆da de presi贸n, an谩lisis qu铆mico r谩pido y, en algunos casos, im谩genes t茅rmicas que muestran zonas con p茅rdida de eficiencia."
        },
        {
            "type": "heading",
            "level": 2,
            "text": "Principios de selecci贸n qu铆mica: 谩cidos vs alcalinos"
        },
        {
            "type": "paragraph",
            "text": "La selecci贸n del agente qu铆mico depende del tipo de contaminante y del material del serpent铆n:"
        },
        {
            "type": "heading",
            "level": 3,
            "text": "Agentes 谩cidos"
        },
        {
            "type": "list",
            "style": "unordered",
            "items": [
                "Indicados para remover dep贸sitos minerales, cal y sarro.",
                "Compuestos t铆picos: 谩cido c铆trico, fosf贸rico o f贸rmico en concentraciones controladas.",
                "Riesgo: corrosi贸n de cobre, aluminio o soldaduras si no se aplican correctamente.",
                "Uso profesional: diluci贸n seg煤n fabricante, monitoreo de pH, neutralizaci贸n posterior con agente alcalino suave."
            ]
        },
        {
            "type": "heading",
            "level": 3,
            "text": "Agentes alcalinos"
        },
        {
            "type": "list",
            "style": "unordered",
            "items": [
                "Indicados para grasas, aceites, contaminantes org谩nicos y suciedad general.",
                "Compuestos t铆picos: hidr贸xido de sodio, carbonatos y detergentes especializados.",
                "Riesgo: da帽o a recubrimientos superficiales y evaporadores si se excede concentraci贸n.",
                "Uso profesional: control de temperatura, tiempo de contacto y enjuague completo."
            ]
        },
        {
            "type": "heading",
            "level": 2,
            "text": "Procedimientos de limpieza qu铆mica avanzada"
        },
        {
            "type": "paragraph",
            "text": "Preparaci贸n del 谩rea y seguridad: Protecci贸n de personal, protecci贸n del entorno (cubiertas), desconexi贸n de unidades y aislamiento el茅ctrico."
        },
        {
            "type": "paragraph",
            "text": "Aplicaci贸n controlada del agente qu铆mico: Pulverizaci贸n uniforme, monitoreo constante de temperatura y concentraci贸n, uso de medidores de pH."
        },
        {
            "type": "paragraph",
            "text": "Neutralizaci贸n y enjuague: Neutralizaci贸n del 谩cido con alcalino o agua tratada, enjuague completo con agua desmineralizada, control de ca铆da de presi贸n y flujo para verificar recuperaci贸n de eficiencia."
        },
        {
            "type": "paragraph",
            "text": "Verificaci贸n post-limpieza: Inspecci贸n visual, pruebas de presi贸n y flujo, medici贸n de eficiencia t茅rmica (Delta T)."
        },
        {
            "type": "heading",
            "level": 2,
            "text": "T茅cnicas avanzadas de aplicaci贸n profesional"
        },
        {
            "type": "list",
            "style": "unordered",
            "items": [
                "Recirculaci贸n cerrada: para limpiar condensadores de agua sin desperdiciar qu铆micos.",
                "Rociado de baja presi贸n y 谩ngulo controlado: evita da帽o a aletas.",
                "Uso de cepillos qu铆micos suaves: acci贸n mec谩nica sin da帽ar superficie.",
                "Sistemas de filtrado previo: eliminan s贸lidos mayores."
            ]
        },
        {
            "type": "heading",
            "level": 2,
            "text": "Seguridad y manejo de qu铆micos"
        },
        {
            "type": "paragraph",
            "text": "El mantenimiento avanzado exige: Uso de EPP completo, monitoreo de ventilaci贸n y vapores, control de derrames y almacenamiento seguro. Un t茅cnico profesional asegura que la limpieza qu铆mica no represente riesgo para la instalaci贸n ni para el personal."
        },
        {
            "type": "heading",
            "level": 2,
            "text": "Optimizaci贸n de eficiencia post-limpieza"
        },
        {
            "type": "paragraph",
            "text": "Tras la limpieza, se realizan ajustes para maximizar eficiencia: Recuperaci贸n de flujo seg煤n dise帽o, verificaci贸n de temperatura, pruebas de presi贸n y documentaci贸n de resultados (mediciones, productos, pH, etc.) para mantenimiento predictivo."
        },
        {
            "type": "heading",
            "level": 3,
            "text": " FOTO REQUERIDA (BUSCAR O GENERAR): Diagrama profesional mostrando un serpent铆n con agente qu铆mico aplicado, flujo de enjuague, puntos de inspecci贸n, neutralizaci贸n y t茅cnicas de pulverizaci贸n segura."
        },
        {
            "type": "heading",
            "level": 2,
            "text": "Conclusi贸n t茅cnica de la lecci贸n"
        },
        {
            "type": "paragraph",
            "text": "La limpieza qu铆mica de serpentines, realizada correctamente con 谩cidos o alcalinos seg煤n tipo de suciedad y material, es un procedimiento cr铆tico en mantenimiento profesional-m谩ster de HVAC. Requiere diagn贸stico previo, selecci贸n qu铆mica precisa, aplicaci贸n controlada, neutralizaci贸n, enjuague y verificaci贸n de eficiencia. El enfoque integral asegura transferencia t茅rmica 贸ptima, protecci贸n del equipo, eficiencia energ茅tica m谩xima y prevenci贸n de fallas, formando parte esencial de cualquier plan de mantenimiento preventivo y predictivo de alto nivel."
        }
    ]
}